donkit/retriever/__init__.py
donkit/retriever/abstractions.py
donkit/retriever/chroma_vectorstore.py
donkit/retriever/milvus_vectorstore.py
donkit/retriever/qdrant_vectorstore.py
donkit/retriever/retrieval_config.py
donkit/retriever/vectorstore_service.py
donkit_retriever-0.1.7.dist-info/METADATA
donkit_retriever-0.1.7.dist-info/WHEEL
donkit_retriever-0.1.7.dist-info/RECORD
