Metadata-Version: 2.4
Name: donkit-retriever
Version: 0.1.7
Summary: Unified retrieval module for RAG system with multiple vector database support
License: MIT
Author: Roman Losev
Author-email: losik19-94@yandex.ru
Requires-Python: >=3.12,<4.0
Classifier: License :: OSI Approved :: MIT License
Classifier: Programming Language :: Python :: 3
Classifier: Programming Language :: Python :: 3.12
Classifier: Programming Language :: Python :: 3.13
Classifier: Programming Language :: Python :: 3.14
Requires-Dist: chromadb (==1.3.4)
Requires-Dist: langchain (>=0.3.27,<0.4.0)
Requires-Dist: langchain-core (>=0.3.79,<0.4.0)
Requires-Dist: loguru (>=0.7.3,<0.8.0)
Requires-Dist: protobuf (==6.33.0)
Requires-Dist: pydantic (>=2.7.4,<3.0.0)
Requires-Dist: pymilvus (==2.6.0)
Requires-Dist: qdrant-client[fastembed] (==1.15.1)
